tdoc/common/__init__.py
tdoc/common/api.py
tdoc/common/api_mod_wsgi.py
tdoc/common/cli.py
tdoc/common/config.py
tdoc/common/console.py
tdoc/common/database.py
tdoc/common/defaults.py
tdoc/common/deps.py
tdoc/common/favicon.svg
tdoc/common/logs.py
tdoc/common/store.py
tdoc/common/theme.toml
tdoc/common/util.py
tdoc/common/wsgi.py
tdoc/common/ext/__init__.py
tdoc/common/ext/defaults.py
tdoc/common/ext/diagram.py
tdoc/common/ext/exec.py
tdoc/common/ext/iframe.py
tdoc/common/ext/layout.py
tdoc/common/ext/math.py
tdoc/common/ext/metadata.py
tdoc/common/ext/num.py
tdoc/common/ext/patch.py
tdoc/common/ext/poll.py
tdoc/common/ext/quiz.py
tdoc/common/ext/solution.py
tdoc/common/ext/table.py
tdoc/common/locale/__init__.py
tdoc/common/python/tdoc/__init__.py
tdoc/common/python/tdoc/core.py
tdoc/common/python/tdoc/pygame.py
tdoc/common/python/tdoc/svg.py
tdoc/common/scripts/editor.js
tdoc/common/scripts/tdoc-worker.js
tdoc/common/static/tdoc/api.js
tdoc/common/static/tdoc/core.js
tdoc/common/static/tdoc/crypto.js
tdoc/common/static/tdoc/domain.html.jinja
tdoc/common/static/tdoc/early.js
tdoc/common/static/tdoc/exec-html-iframe.js
tdoc/common/static/tdoc/exec-html.js
tdoc/common/static/tdoc/exec-micropython.js
tdoc/common/static/tdoc/exec-python.js
tdoc/common/static/tdoc/exec-python.py
tdoc/common/static/tdoc/exec-sql.js
tdoc/common/static/tdoc/exec.js
tdoc/common/static/tdoc/jsxgraph.js
tdoc/common/static/tdoc/load.js
tdoc/common/static/tdoc/micropython.js
tdoc/common/static/tdoc/poll.js
tdoc/common/static/tdoc/print-common.css
tdoc/common/static/tdoc/print-exam.css
tdoc/common/static/tdoc/print.css
tdoc/common/static/tdoc/quiz.js
tdoc/common/static/tdoc/serial.js
tdoc/common/static/tdoc/styles.css
tdoc/common/static.gen/sabayon-listeners.js
tdoc/common/static.gen/tdoc/editor.js
tdoc/common/templates/copyright.html
t_doc_common-0.68.dist-info/METADATA
t_doc_common-0.68.dist-info/WHEEL
t_doc_common-0.68.dist-info/entry_points.txt
t_doc_common-0.68.dist-info/licenses/LICENSE.txt
t_doc_common-0.68.dist-info/licenses/LICENSES.deps.txt
t_doc_common-0.68.dist-info/RECORD
